{
    "title": "Regulamin ćwiczeń z Podstaw programowania",
    "date": "21.09.2025",
    "description": "Kierunek AiR, W12, PWR",
    "articles": [
        {
            "title": "Cel Kursu",
            "clauses": [
                "Celem kursu jest dostarczenie studentom wiedzy związanej z tematyką algorytmiki i tworzenia oprogramowania."
            ]
        },
        {
            "title": "Organizacja Kursu",
            "clauses": [
                "Kurs obejmuje 8 spotkań.",
                "Kurs odbywa się w formie ćwiczeń.",
                "Kurs wymaga samodzielnej pracy w domu."
            ]
        },
        {
            "title": "Obecność na zajęciach",
            "clauses": [
                "Obecność na ćwiczeniach jest obowiązkowa.",
                "Dopuszczalna jest <span class='red_c'>jedna</span> nieobecność niezależnie od jej przyczyny.",                
                "W przypadku wyjątkowych sytuacji (np. hospitalizacja, wypadek, problemy rodzinne), które mogą skutkować większą liczbą nieobecności niż dopuszczona, konieczny jest <span class='red_c'>stały kontakt z prowadzącą</span>. Brak kontaktu skutkuje oceną niedostateczną (2.0) z przedmiotu.",
                "Nie ma możliwości zaliczenia ćwiczeń w trybie skumulowanym na koniec semestru. Uczestnictwo w zajęciach musi odbywać się na bieżąco, zgodnie z harmonogramem."
            ]
        },
        {
            "title": "Przebieg Zajęć",
            "clauses": [
                "Przed przyjściem na ćwiczenia należy zapoznać się z treścią zadań i wykonać je. Należy również przygotować się z treści wykładu.",
                "Podczas zajęć ćwiczeniowych sprawdzana jest obecność a następnie odbywa się kolokwium cząstkowe z zadań analogicznych do tych, które są na <a href='?page=pp' >obowiązujących listach</a>.",
                "Następnie wykonywane są wybrane zadania (z listy lub spoza niej) przez osoby wyznaczone przez prowadzącą lub w grupie.",
                "Na koniec przeprowadzona jest Haszówka."
            ]
        },
        {
            "title": "Zaliczenie kursu",
            "clauses": [
                {
                    "title": "Zaliczenie ćwiczeń odbywa się na podstawie 2 kryteriów, które muszą być spełnione równocześnie:",
                    "points": [
                        "obecności na minimum 7 zajęciach z 8",
                        "uzyskanie minimum 50% z każdego kolokwium cząstkowego lub z kolokwium poprawkowego"
                    ]
                },
                "Po spełnieniu 2 kryteriów obliczona jest ocena końcowa na podstawie sumy punktów ze wszystkich kolokwiów cząstkowych lub punktów z kolokwium poprawkowego według progów.",
                {
                    "title": "Progi punktowe na poszczególne oceny:",
                    "type": "none_style",
                    "points": [
                        "<strong class='w-25 d-inline-block '>2.0</strong> 0 – 49.99%",
                        "<strong class='w-25 d-inline-block '>3.0</strong> 50 – 59.99%",
                        "<strong class='w-25 d-inline-block '>3.5</strong> 60 – 69.99%",
                        "<strong class='w-25 d-inline-block '>4.0</strong> 70 – 79.99%",
                        "<strong class='w-25 d-inline-block '>4.5</strong> 80 – 89.99%",
                        "<strong class='w-25 d-inline-block '>5.0</strong> 90 – 100%"
                    ]
                }
            ]
        },
        {
            "title": "Kolokwium",
            "clauses": [
                "Kolokwium zaliczeniowe składa się z kilku kolokwiów cząstkowych K1, K2, K3, .., itd które są realizowane sukcesywnie w trakcie semestru na początku każdych zajęć.",                
                "Na zajęciach obowiązuje znajomość materiału ze wszystkich poprzednich ćwiczeń oraz wykładów. Na kolokwium pojawią się jednak wyłącznie zadania analogiczne do tych zamieszczonych na listach oznaczonych jako 'ukończona' oraz 'przygotowana' dla danego numeru ćwiczeń.",                
                "W przypadku jednej dozwolonej nieobecności student ma możliwość napisania kolokwium cząstkowego podczas konsultacji, nie później niż 10 dni po ustaniu przyczyny nieobecności (z wyłączeniem sobót, niedziel i świąt).",
                "W przypadku nieuzyskania pozytywnej oceny student ma możliwość przystąpienia do ponownej weryfikacji efektów uczenia się w formie poprawkowego kolokwium zaliczeniowego obejmującego materiał z całego semestru.",
                "Termin poprawy kolokwium wyznacza prowadząca na początku semestru i umieszcza w części górnej strony przedmiotu w ePortalu.",
                "Podczas konsultacji możliwe jest napisanie kolokwium cząstkowego w przypadku dozwolonej nieobecności. Poprawa niezaliczonych kolokwiów cząstkowych nie jest możliwa. W takim przypadku student może przystąpić do poprawkowego kolokwium zaliczeniowego z całego semestru w wyznaczonym terminie."
            ]
        },
        {
            "title": "Haszówki",
            "clauses": [
                "W trakcie zajęć będą odbywać się haszówki, których wyniki mają wpływ na ocenę z wykładu, ale nie wpływają na ocenę z ćwiczeń.",
                "W przypadku nieobecności lub problemów technicznych student ma prawo do zaliczenia opuszczonej haszówki na najbliższych konsultacjach."
            ]
        },
        {
            "title": "Szczególne Potrzeby",
            "clauses": [
                "Studenci, którzy mają szczególne potrzeby związane ze sposobem realizacji zajęć, zaliczenia lub przygotowaniem materiałów, proszeni są o zgłoszenie się na konsultacje lub po zajęciach, aby omówić te indywidualne potrzeby."
            ]
        },
        {
            "title": "Postanowienia Końcowe oraz BHP",
            "clauses": [
                "Regulamin ten jest ważny przez cały okres trwania zajęć.",
                "Prowadząca zajęcia zastrzega sobie prawo do dokonywania zmian w regulaminie w trakcie trwania zajęć. Studentom zostaną udzielone stosowne informacje o takich zmianach.",
                "Każdy student, zapisując się na zajęcia, zobowiązuje się do przestrzegania tego regulaminu.",
                "W przypadku naruszenia tego regulaminu, prowadząca ma prawo podjąć odpowiednie kroki, włącznie z wystawieniem studentowi oceny niedostatecznej z kursu.",
                "Należy przestrzegać zasad BHP oraz regulaminu wywieszonego w sali laboratoryjnej.",
                "Wszelkie sytuacje nieopisane w regulaminie rozpatrywane są indywidualnie przez prowadzącą.",
                "Uwagi do niniejszego regulaminu proszę zgłaszać mailowo."
            ]
        }
    
    ]
}